{
  "interpret": "Anna K.",
  "nazev": "Zavírám oči",
  "text": "INTRO: [A] [C#mi] [F#mi] 2x\n\n[A]Jednou se nám [C#mi]může zdát, [F#mi]co jsme byli dřív.\n[A]Ráno stopy [C#mi]nejsou znát, když [F#mi]večer padal sníh.\n\n\nREF :\n[Bmi]Jsou věci jiný, něco [D]víc…\n[A]Zavírám oči, nenech mě [E]říct…\n\nMálo tě [A]znám,\nmálo tě [B#mi]znám,\nMálo tě [D]znám,\nMálo tě [A]znám….\n\n[A]Možná se už [C#mi]nedozvíš, [F#mi]jak to bylo dál.\n[A]Po čem takhle [C#mi]dlouho spíš a [F#mi]že jsi se i smál\n\nREF :\n[Bmi]Jsou věci jiný, něco [D]víc…\n[A]Zavírám oči, nenech mě [E]říct…\n[Bmi]Jsou věci jiný, něco [D]víc…\n[A]Zavírám oči, nenech mě [E]říct…\n\nMálo tě [A]znám,\nmálo tě [B#mi]znám,\nMálo tě [D]znám,\nMálo tě [A]znám….\n\nMEZIHRA: [A] [C#mi] [F#mi]\n\nREF :\n[Bmi]Jsou věci jiný, něco [D]víc…\n[A]Zavírám oči, nenech mě [E]říct…\n\nMálo tě [A]znám,\nmálo tě [B#mi]znám,\nMálo tě [D]znám,\nMálo tě [A]znám….\nMálo tě [B#mi]znám, (jsou věci jiný)\nMálo tě [D]znám, (jsou věci jiný)\nMálo tě [A]znám, (jsou věci jiný)\nMálo tě [B#mi]znám, (jsou věci jiný)\nMálo tě [D]znám, (jsou věci jiný)\nMálo tě [D]znám, (jsou věci jiný)\n\n(do ztracena….)",
  "tonina": "A",
  "kapodastr": "",
  "used_chords": "A,C#mi,F#mi,Hmi,D,E"
}